Workbook

Sheet Loan info
A2: Loan number | B2: 110022
A3: Current date | B3: 44845
A4: Origination Date | B4: 44846
A5: First Payment date | B5: 44855
A6: Payment frequency | B6: Monthly
A7: principal | B7: 2500
A8: annual nominal rate | B8: 0.475
A9: number of payments | B9: 12
B11: Name | C11: Address | D11: Phone | E11: Email | F11: Bank Transit | G11: Bank Institution | H11: Bank Account
A12: Borrower | B12: John Doe | C12: 123 AAA St | D12: 111-222-2222 | E12: john.doe@gmail.com | F12: 98988 | G12: 004 | H12: 1212345
A13: Cosigner 1 | B13: Bo Be | C13: 234 BBB St | D13: 111-222-3333 | E13: bo.be@gmail.com
A14: Cosigner 2 | B14: Sam Yan | C14: 888 CCC St | D14: 999-000-9999 | E14: sam.yan@gmail.com
A15: Cosigner 3 | B15: Mike Dow | C15: 999 DDD St | D15: 939-020-3933 | E15: mike.dow@gmail.com
A20: https://docs.google.com/open?id=1oyfclZRXYLG3dRCrdV1zCtalXqlfe6PhDGO9eSEYu4w

Sheet Details and table
A1: Loan number | B1: ='Loan info'!B2 -> 110022 | D1: Line | E1: * Line status | F1: * Pmt Date | G1: * Payment | H1: * Rate | I1: Mathematical Principal | J1: Accrued Interest | K1: days portion (hide) | L1: Mathematical Principal | M1: Accrued Interest | N1: fees | O1: Balance | P1: Balance | Q1: * Comment | R1: Paid Interest | S1: Paid Principal | T1: Balance Due Interest | U1: Balance Due Principal
A2: Current date | B2: ='Loan info'!B3 -> 44845 | D2: 1 | E2: Due Pmt | F2: =B4 -> 44855 | G2: =B10 -> 258.65225 | H2: =$B$7 -> 0.475 | I2: 91.64 | J2: 28.88 | K2: =IF(D2="","",IF(MONTH(B3)=MONTH(F2),(F2-B3)/DAY(EOMONTH(F2,0)),DAY(EOMONTH(B3,0)-B3)/DAY(EOMONTH(B3,0))+DAY(F2-EOMONTH(B3,0))/DAY(EOMONTH(F2,0)))) -> 0.29032258 | L2: =IF(D2="","",G2-M2) -> 230.31708 | M2: =IF(D2="","",B6*((1+$B$7/12)^(K2)-1)) -> 28.335174 | O2: =IF(D2="","",B6+M2-G2+N2) -> 2269.6829 | P2: 2408.36 | R2: 0 | S2: 0 | T2: =M2 -> 28.335174 | U2: =B6 -> 2500
A3: Origination Date | B3: ='Loan info'!B4 -> 44846 | D3: =IF(D2="", "",IF(D2+1>$B$8,"",D2+1)) -> 2 | E3: =IF(D3="","","Due Pmt") -> Due Pmt | F3: =IF(D3="", "", IF($B$5="Byweekly", F2+14,IF($B$5="End of month",EOMONTH(F2, 1),EDATE($F$2,D3-1)))) -> 44886 | G3: =IF(D3="","",$G$2) -> 258.65225 | H3: =$B$7 -> 0.475 | I3: 77.1 | J3: 43.42 | K3: =IF(D3="","",IF(MONTH(F2)=MONTH(F3),(F3-F2)/DAY(EOMONTH(F3,0)),DAY(EOMONTH(F2,0)-F2)/DAY(EOMONTH(F2,0))+DAY(F3-EOMONTH(F2,0))/DAY(EOMONTH(F3,0)))) -> 0.95698925 | L3: =IF(D3="","",G3-M3) -> 172.74699 | M3: =IF(D3="","",O2*((1+$B$7/12)^(K3)-1)) -> 85.905259 | O3: =IF(D3="","",O2+M3-G3+N3) -> 2096.9359 | P3: 2331.26 | R3: 0 | S3: 0 | T3: =T2+M3 -> 114.24043 | U3: 2500
A4: First Payment date | B4: ='Loan info'!B5 -> 44855 | D4: =IF(D3="", "",IF(D3+1>$B$8,"",D3+1)) -> 3 | E4: =IF(D4="","","Due Pmt") -> Due Pmt | F4: =IF(D4="", "", IF($B$5="Byweekly", F3+14,IF($B$5="End of month",EOMONTH(F3, 1),EDATE($F$2,D4-1)))) -> 44916 | G4: =IF(D4="","",$G$2) -> 258.65225 | H4: =$B$7 -> 0.475 | I4: 78.49 | J4: 42.03 | K4: =IF(D4="","",IF(MONTH(F3)=MONTH(F4),(F4-F3)/DAY(EOMONTH(F4,0)),DAY(EOMONTH(F3,0)-F3)/DAY(EOMONTH(F3,0))+DAY(F4-EOMONTH(F3,0))/DAY(EOMONTH(F4,0)))) -> 0.91182796 | L4: =IF(D4="","",G4-M4) -> 183.09736 | M4: =IF(D4="","",O3*((1+$B$7/12)^(K4)-1)) -> 75.554889 | O4: =IF(D4="","",O3+M4-G4+N4) -> 1913.8386 | P4: 2252.77 | R4: 0 | S4: 0 | T4: =T3+M4 -> 189.79532 | U4: 2500
A5: Payment frequency | B5: ='Loan info'!B6 -> Monthly | D5: =IF(D4="", "",IF(D4+1>$B$8,"",D4+1)) -> 4 | E5: =IF(D5="","","Due Pmt") -> Due Pmt | F5: =IF(D5="", "", IF($B$5="Byweekly", F4+14,IF($B$5="End of month",EOMONTH(F4, 1),EDATE($F$2,D5-1)))) -> 44947 | G5: =IF(D5="","",$G$2) -> 258.65225 | H5: =$B$7 -> 0.475 | I5: 79.91 | J5: 40.61 | K5: =IF(D5="","",IF(MONTH(F4)=MONTH(F5),(F5-F4)/DAY(EOMONTH(F5,0)),DAY(EOMONTH(F4,0)-F4)/DAY(EOMONTH(F4,0))+DAY(F5-EOMONTH(F4,0))/DAY(EOMONTH(F5,0)))) -> 0.93548387 | L5: =IF(D5="","",G5-M5) -> 187.87288 | M5: =IF(D5="","",O4*((1+$B$7/12)^(K5)-1)) -> 70.779374 | O5: =IF(D5="","",O4+M5-G5+N5) -> 1725.9657 | P5: 2172.86 | R5: 0 | S5: 0 | T5: =T4+M5 -> 260.5747 | U5: 2500
A6: principal | B6: ='Loan info'!B7 -> 2500 | D6: =IF(D5="", "",IF(D5+1>$B$8,"",D5+1)) -> 5 | E6: =IF(D6="","","Due Pmt") -> Due Pmt | F6: =IF(D6="", "", IF($B$5="Byweekly", F5+14,IF($B$5="End of month",EOMONTH(F5, 1),EDATE($F$2,D6-1)))) -> 44978 | G6: =IF(D6="","",$G$2) -> 258.65225 | H6: =$B$7 -> 0.475 | I6: 81.35 | J6: 39.17 | K6: =IF(D6="","",IF(MONTH(F5)=MONTH(F6),(F6-F5)/DAY(EOMONTH(F6,0)),DAY(EOMONTH(F5,0)-F5)/DAY(EOMONTH(F5,0))+DAY(F6-EOMONTH(F5,0))/DAY(EOMONTH(F6,0)))) -> 1.0046083 | L6: =IF(D6="","",G6-M6) -> 190.01176 | M6: =IF(D6="","",O5*((1+$B$7/12)^(K6)-1)) -> 68.640491 | O6: =IF(D6="","",O5+M6-G6+N6) -> 1535.9539 | P6: 2091.51 | R6: 0 | S6: 0 | T6: =T5+M6 -> 329.21519 | U6: 2500
A7: annual nominal rate | B7: ='Loan info'!B8 -> 0.475 | D7: =IF(D6="", "",IF(D6+1>$B$8,"",D6+1)) -> 6 | E7: =IF(D7="","","Due Pmt") -> Due Pmt | F7: =IF(D7="", "", IF($B$5="Byweekly", F6+14,IF($B$5="End of month",EOMONTH(F6, 1),EDATE($F$2,D7-1)))) -> 45006 | G7: =IF(D7="","",$G$2) -> 258.65225 | H7: =$B$7 -> 0.475 | I7: 82.81 | J7: 37.71 | K7: =IF(D7="","",IF(MONTH(F6)=MONTH(F7),(F7-F6)/DAY(EOMONTH(F7,0)),DAY(EOMONTH(F6,0)-F6)/DAY(EOMONTH(F6,0))+DAY(F7-EOMONTH(F6,0))/DAY(EOMONTH(F7,0)))) -> 0.859447 | L7: =IF(D7="","",G7-M7) -> 206.54265 | M7: =IF(D7="","",O6*((1+$B$7/12)^(K7)-1)) -> 52.109597 | O7: =IF(D7="","",O6+M7-G7+N7) -> 1329.4113 | P7: 2008.7 | R7: 0 | S7: 0 | T7: =T6+M7 -> 381.32478 | U7: 2500
A8: number of payments | B8: ='Loan info'!B9 -> 12 | D8: =IF(D7="", "",IF(D7+1>$B$8,"",D7+1)) -> 7 | E8: =IF(D8="","","Due Pmt") -> Due Pmt | F8: =IF(D8="", "", IF($B$5="Byweekly", F7+14,IF($B$5="End of month",EOMONTH(F7, 1),EDATE($F$2,D8-1)))) -> 45037 | G8: =IF(D8="","",$G$2) -> 258.65225 | H8: =$B$7 -> 0.475 | I8: 84.31 | J8: 36.21 | K8: =IF(D8="","",IF(MONTH(F7)=MONTH(F8),(F8-F7)/DAY(EOMONTH(F8,0)),DAY(EOMONTH(F7,0)-F7)/DAY(EOMONTH(F7,0))+DAY(F8-EOMONTH(F7,0))/DAY(EOMONTH(F8,0)))) -> 0.95698925 | L8: =IF(D8="","",G8-M8) -> 208.33534 | M8: =IF(D8="","",O7*((1+$B$7/12)^(K8)-1)) -> 50.316905 | O8: =IF(D8="","",O7+M8-G8+N8) -> 1121.0759 | P8: 1924.39 | R8: 0 | S8: 0 | T8: =T7+M8 -> 431.64169 | U8: 2500
D9: =IF(D8="", "",IF(D8+1>$B$8,"",D8+1)) -> 8 | E9: =IF(D9="","","Due Pmt") -> Due Pmt | F9: =IF(D9="", "", IF($B$5="Byweekly", F8+14,IF($B$5="End of month",EOMONTH(F8, 1),EDATE($F$2,D9-1)))) -> 45067 | G9: =IF(D9="","",$G$2) -> 258.65225 | H9: =$B$7 -> 0.475 | I9: 85.83 | J9: 34.69 | K9: =IF(D9="","",IF(MONTH(F8)=MONTH(F9),(F9-F8)/DAY(EOMONTH(F9,0)),DAY(EOMONTH(F8,0)-F8)/DAY(EOMONTH(F8,0))+DAY(F9-EOMONTH(F8,0))/DAY(EOMONTH(F9,0)))) -> 0.91182796 | L9: =IF(D9="","",G9-M9) -> 218.25866 | M9: =IF(D9="","",O8*((1+$B$7/12)^(K9)-1)) -> 40.393589 | O9: =IF(D9="","",O8+M9-G9+N9) -> 902.81728 | P9: 1838.56 | R9: 0 | S9: 0 | T9: =T8+M9 -> 472.03528 | U9: 2500
A10: payment amount | B10: 258.65225 | C10: Goal Seek for balance =0 | D10: =IF(D9="", "",IF(D9+1>$B$8,"",D9+1)) -> 9 | E10: =IF(D10="","","Due Pmt") -> Due Pmt | F10: =IF(D10="", "", IF($B$5="Byweekly", F9+14,IF($B$5="End of month",EOMONTH(F9, 1),EDATE($F$2,D10-1)))) -> 45098 | G10: =IF(D10="","",$G$2) -> 258.65225 | H10: =$B$7 -> 0.475 | I10: 87.37 | J10: 33.15 | K10: =IF(D10="","",IF(MONTH(F9)=MONTH(F10),(F10-F9)/DAY(EOMONTH(F10,0)),DAY(EOMONTH(F9,0)-F9)/DAY(EOMONTH(F9,0))+DAY(F10-EOMONTH(F9,0))/DAY(EOMONTH(F10,0)))) -> 0.95698925 | L10: =IF(D10="","",G10-M10) -> 224.48151 | M10: =IF(D10="","",O9*((1+$B$7/12)^(K10)-1)) -> 34.170743 | O10: =IF(D10="","",O9+M10-G10+N10) -> 678.33577 | P10: 1751.19 | R10: 0 | S10: 0 | T10: =T9+M10 -> 506.20602 | U10: 2500
D11: =IF(D10="", "",IF(D10+1>$B$8,"",D10+1)) -> 10 | E11: =IF(D11="","","Due Pmt") -> Due Pmt | F11: =IF(D11="", "", IF($B$5="Byweekly", F10+14,IF($B$5="End of month",EOMONTH(F10, 1),EDATE($F$2,D11-1)))) -> 45128 | G11: =IF(D11="","",$G$2) -> 258.65225 | H11: =$B$7 -> 0.475 | I11: 88.95 | J11: 31.57 | K11: =IF(D11="","",IF(MONTH(F10)=MONTH(F11),(F11-F10)/DAY(EOMONTH(F11,0)),DAY(EOMONTH(F10,0)-F10)/DAY(EOMONTH(F10,0))+DAY(F11-EOMONTH(F10,0))/DAY(EOMONTH(F11,0)))) -> 0.91182796 | L11: =IF(D11="","",G11-M11) -> 234.21107 | M11: =IF(D11="","",O10*((1+$B$7/12)^(K11)-1)) -> 24.441178 | O11: =IF(D11="","",O10+M11-G11+N11) -> 444.1247 | P11: 1662.24 | R11: 0 | S11: 0 | T11: =T10+M11 -> 530.6472 | U11: 2500
A12: Norminal Rate | D12: =IF(D11="", "",IF(D11+1>$B$8,"",D11+1)) -> 11 | E12: =IF(D12="","","Due Pmt") -> Due Pmt | F12: =IF(D12="", "", IF($B$5="Byweekly", F11+14,IF($B$5="End of month",EOMONTH(F11, 1),EDATE($F$2,D12-1)))) -> 45159 | G12: =IF(D12="","",$G$2) -> 258.65225 | H12: =$B$7 -> 0.475 | I12: 90.55 | J12: 29.97 | K12: =IF(D12="","",IF(MONTH(F11)=MONTH(F12),(F12-F11)/DAY(EOMONTH(F12,0)),DAY(EOMONTH(F11,0)-F11)/DAY(EOMONTH(F11,0))+DAY(F12-EOMONTH(F11,0))/DAY(EOMONTH(F12,0)))) -> 0.93548387 | L12: =IF(D12="","",G12-M12) -> 242.22721 | M12: =IF(D12="","",O11*((1+$B$7/12)^(K12)-1)) -> 16.425036 | O12: =IF(D12="","",O11+M12-G12+N12) -> 201.89749 | P12: 1571.69 | R12: 0 | S12: 0 | T12: =T11+M12 -> 547.07224 | U12: 2500
A13: Norminal | B13: =B7 -> 0.475 | D13: =IF(D12="", "",IF(D12+1>$B$8,"",D12+1)) -> 12 | E13: =IF(D13="","","Due Pmt") -> Due Pmt | F13: =IF(D13="", "", IF($B$5="Byweekly", F12+14,IF($B$5="End of month",EOMONTH(F12, 1),EDATE($F$2,D13-1)))) -> 45190 | G13: =IF(D13="","",$G$2) -> 258.65225 | H13: =$B$7 -> 0.475 | I13: 92.18 | J13: 28.34 | K13: =IF(D13="","",IF(MONTH(F12)=MONTH(F13),(F13-F12)/DAY(EOMONTH(F13,0)),DAY(EOMONTH(F12,0)-F12)/DAY(EOMONTH(F12,0))+DAY(F13-EOMONTH(F12,0))/DAY(EOMONTH(F13,0)))) -> 0.95698925 | L13: =IF(D13="","",G13-M13) -> 251.01063 | M13: =IF(D13="","",O12*((1+$B$7/12)^(K13)-1)) -> 7.6416206 | O13: =IF(D13="","",O12+M13-G13+N13) -> -49.113143 | P13: 1479.51 | R13: 0 | S13: 0 | T13: =T12+M13 -> 554.71386 | U13: 2500
A14: Effective | B14: =ROUND((1+B13/12)^12-1,4) -> 0.5934 | D14: =IF(D13="", "",IF(D13+1>$B$8,"",D13+1)) | E14: =IF(D14="","","Due Pmt") | F14: =IF(D14="", "", IF($B$5="Byweekly", F13+14,IF($B$5="End of month",EOMONTH(F13, 1),EDATE($F$2,D14-1)))) | G14: =IF(D14="","",$G$2) | H14: =$B$7 -> 0.475 | I14: 93.85 | J14: 26.67 | K14: =IF(D14="","",IF(MONTH(F13)=MONTH(F14),(F14-F13)/DAY(EOMONTH(F14,0)),DAY(EOMONTH(F13,0)-F13)/DAY(EOMONTH(F13,0))+DAY(F14-EOMONTH(F13,0))/DAY(EOMONTH(F14,0)))) | L14: =IF(D14="","",G14-M14) | M14: =IF(D14="","",O13*((1+$B$7/12)^(K14)-1)) | O14: =IF(D14="","",O13+M14-G14+N14) | P14: 1385.66 | R14: 0 | S14: 0 | T14: =T13+M14 -> 554.71386 | U14: 2500
A15: APR | D15: =IF(D14="", "",IF(D14+1>$B$8,"",D14+1)) | E15: =IF(D15="","","Due Pmt") | F15: =IF(D15="", "", IF($B$5="Byweekly", F14+14,IF($B$5="End of month",EOMONTH(F14, 1),EDATE($F$2,D15-1)))) | G15: =IF(D15="","",$G$2) | H15: =$B$7 -> 0.475 | I15: 95.54 | J15: 24.98 | K15: =IF(D15="","",IF(MONTH(F14)=MONTH(F15),(F15-F14)/DAY(EOMONTH(F15,0)),DAY(EOMONTH(F14,0)-F14)/DAY(EOMONTH(F14,0))+DAY(F15-EOMONTH(F14,0))/DAY(EOMONTH(F15,0)))) | L15: =IF(D15="","",G15-M15) | M15: =IF(D15="","",O14*((1+$B$7/12)^(K15)-1)) | O15: =IF(D15="","",O14+M15-G15+N15) | P15: 1290.12 | R15: 0 | S15: 0 | T15: =T14+M15 -> 554.71386 | U15: 2500
A16: Norminal | B16: =B13 -> 0.475 | D16: =IF(D15="", "",IF(D15+1>$B$8,"",D15+1)) | E16: =IF(D16="","","Due Pmt") | F16: =IF(D16="", "", IF($B$5="Byweekly", F15+14,IF($B$5="End of month",EOMONTH(F15, 1),EDATE($F$2,D16-1)))) | G16: =IF(D16="","",$G$2) | H16: =$B$7 -> 0.475 | I16: 97.26 | J16: 23.26 | K16: =IF(D16="","",IF(MONTH(F15)=MONTH(F16),(F16-F15)/DAY(EOMONTH(F16,0)),DAY(EOMONTH(F15,0)-F15)/DAY(EOMONTH(F15,0))+DAY(F16-EOMONTH(F15,0))/DAY(EOMONTH(F16,0)))) | L16: =IF(D16="","",G16-M16) | M16: =IF(D16="","",O15*((1+$B$7/12)^(K16)-1)) | O16: =IF(D16="","",O15+M16-G16+N16) | P16: 1192.86 | R16: 0 | S16: 0 | T16: =T15+M16 -> 554.71386 | U16: 2500
A17: Effective | B17: =(1+B16/12)^12-1 -> 0.59335189 | D17: =IF(D16="", "",IF(D16+1>$B$8,"",D16+1)) | E17: =IF(D17="","","Due Pmt") | F17: =IF(D17="", "", IF($B$5="Byweekly", F16+14,IF($B$5="End of month",EOMONTH(F16, 1),EDATE($F$2,D17-1)))) | G17: =IF(D17="","",$G$2) | H17: =$B$7 -> 0.475 | I17: 99.01 | J17: 21.51 | K17: =IF(D17="","",IF(MONTH(F16)=MONTH(F17),(F17-F16)/DAY(EOMONTH(F17,0)),DAY(EOMONTH(F16,0)-F16)/DAY(EOMONTH(F16,0))+DAY(F17-EOMONTH(F16,0))/DAY(EOMONTH(F17,0)))) | L17: =IF(D17="","",G17-M17) | M17: =IF(D17="","",O16*((1+$B$7/12)^(K17)-1)) | O17: =IF(D17="","",O16+M17-G17+N17) | P17: 1093.85 | R17: 0 | S17: 0 | T17: =T16+M17 -> 554.71386 | U17: 2500
D18: =IF(D17="", "",IF(D17+1>$B$8,"",D17+1)) | E18: =IF(D18="","","Due Pmt") | F18: =IF(D18="", "", IF($B$5="Byweekly", F17+14,IF($B$5="End of month",EOMONTH(F17, 1),EDATE($F$2,D18-1)))) | G18: =IF(D18="","",$G$2) | H18: =$B$7 -> 0.475 | I18: 100.8 | J18: 19.72 | K18: =IF(D18="","",IF(MONTH(F17)=MONTH(F18),(F18-F17)/DAY(EOMONTH(F18,0)),DAY(EOMONTH(F17,0)-F17)/DAY(EOMONTH(F17,0))+DAY(F18-EOMONTH(F17,0))/DAY(EOMONTH(F18,0)))) | L18: =IF(D18="","",G18-M18) | M18: =IF(D18="","",O17*((1+$B$7/12)^(K18)-1)) | O18: =IF(D18="","",O17+M18-G18+N18) | P18: 993.05 | R18: 0 | S18: 0 | T18: =T17+M18 -> 554.71386 | U18: 2500
A19: Compounding period | B19: Monthly | D19: =IF(D18="", "",IF(D18+1>$B$8,"",D18+1)) | E19: =IF(D19="","","Due Pmt") | F19: =IF(D19="", "", IF($B$5="Byweekly", F18+14,IF($B$5="End of month",EOMONTH(F18, 1),EDATE($F$2,D19-1)))) | G19: =IF(D19="","",$G$2) | H19: =$B$7 -> 0.475 | I19: 102.62 | J19: 17.9 | K19: =IF(D19="","",IF(MONTH(F18)=MONTH(F19),(F19-F18)/DAY(EOMONTH(F19,0)),DAY(EOMONTH(F18,0)-F18)/DAY(EOMONTH(F18,0))+DAY(F19-EOMONTH(F18,0))/DAY(EOMONTH(F19,0)))) | L19: =IF(D19="","",G19-M19) | M19: =IF(D19="","",O18*((1+$B$7/12)^(K19)-1)) | O19: =IF(D19="","",O18+M19-G19+N19) | P19: 890.43 | R19: 0 | S19: 0 | T19: =T18+M19 -> 554.71386 | U19: 2500
A20: last payment due | B20: =INDIRECT(ADDRESS(B8+1,6)) -> 45190 | D20: =IF(D19="", "",IF(D19+1>$B$8,"",D19+1)) | E20: =IF(D20="","","Due Pmt") | F20: =IF(D20="", "", IF($B$5="Byweekly", F19+14,IF($B$5="End of month",EOMONTH(F19, 1),EDATE($F$2,D20-1)))) | G20: =IF(D20="","",$G$2) | H20: =$B$7 -> 0.475 | I20: 104.47 | J20: 16.05 | K20: =IF(D20="","",IF(MONTH(F19)=MONTH(F20),(F20-F19)/DAY(EOMONTH(F20,0)),DAY(EOMONTH(F19,0)-F19)/DAY(EOMONTH(F19,0))+DAY(F20-EOMONTH(F19,0))/DAY(EOMONTH(F20,0)))) | L20: =IF(D20="","",G20-M20) | M20: =IF(D20="","",O19*((1+$B$7/12)^(K20)-1)) | O20: =IF(D20="","",O19+M20-G20+N20) | P20: 785.96 | R20: 0 | S20: 0 | T20: =T19+M20 -> 554.71386 | U20: 2500
A21: Total Interest | B21: =M30 -> 554.71 | D21: =IF(D20="", "",IF(D20+1>$B$8,"",D20+1)) | E21: =IF(D21="","","Due Pmt") | F21: =IF(D21="", "", IF($B$5="Byweekly", F20+14,IF($B$5="End of month",EOMONTH(F20, 1),EDATE($F$2,D21-1)))) | G21: =IF(D21="","",$G$2) | H21: =$B$7 -> 0.475 | I21: 106.35 | J21: 14.17 | K21: =IF(D21="","",IF(MONTH(F20)=MONTH(F21),(F21-F20)/DAY(EOMONTH(F21,0)),DAY(EOMONTH(F20,0)-F20)/DAY(EOMONTH(F20,0))+DAY(F21-EOMONTH(F20,0))/DAY(EOMONTH(F21,0)))) | L21: =IF(D21="","",G21-M21) | M21: =IF(D21="","",O20*((1+$B$7/12)^(K21)-1)) | O21: =IF(D21="","",O20+M21-G21+N21) | P21: 679.61 | R21: 0 | S21: 0 | T21: =T20+M21 -> 554.71386 | U21: 2500
D22: =IF(D21="", "",IF(D21+1>$B$8,"",D21+1)) | E22: =IF(D22="","","Due Pmt") | F22: =IF(D22="", "", IF($B$5="Byweekly", F21+14,IF($B$5="End of month",EOMONTH(F21, 1),EDATE($F$2,D22-1)))) | G22: =IF(D22="","",$G$2) | H22: =$B$7 -> 0.475 | I22: 108.27 | J22: 12.25 | K22: =IF(D22="","",IF(MONTH(F21)=MONTH(F22),(F22-F21)/DAY(EOMONTH(F22,0)),DAY(EOMONTH(F21,0)-F21)/DAY(EOMONTH(F21,0))+DAY(F22-EOMONTH(F21,0))/DAY(EOMONTH(F22,0)))) | L22: =IF(D22="","",G22-M22) | M22: =IF(D22="","",O21*((1+$B$7/12)^(K22)-1)) | O22: =IF(D22="","",O21+M22-G22+N22) | P22: 571.34 | R22: 0 | S22: 0 | T22: =T21+M22 -> 554.71386 | U22: 2500
D23: =IF(D22="", "",IF(D22+1>$B$8,"",D22+1)) | E23: =IF(D23="","","Due Pmt") | F23: =IF(D23="", "", IF($B$5="Byweekly", F22+14,IF($B$5="End of month",EOMONTH(F22, 1),EDATE($F$2,D23-1)))) | G23: =IF(D23="","",$G$2) | H23: =$B$7 -> 0.475 | I23: 110.22 | J23: 10.3 | K23: =IF(D23="","",IF(MONTH(F22)=MONTH(F23),(F23-F22)/DAY(EOMONTH(F23,0)),DAY(EOMONTH(F22,0)-F22)/DAY(EOMONTH(F22,0))+DAY(F23-EOMONTH(F22,0))/DAY(EOMONTH(F23,0)))) | L23: =IF(D23="","",G23-M23) | M23: =IF(D23="","",O22*((1+$B$7/12)^(K23)-1)) | O23: =IF(D23="","",O22+M23-G23+N23) | P23: 461.12 | R23: 0 | S23: 0 | T23: =T22+M23 -> 554.71386 | U23: 2500
A24: Total obligation | B24: =L30 -> 2549.1131 | D24: =IF(D23="", "",IF(D23+1>$B$8,"",D23+1)) | E24: =IF(D24="","","Due Pmt") | F24: =IF(D24="", "", IF($B$5="Byweekly", F23+14,IF($B$5="End of month",EOMONTH(F23, 1),EDATE($F$2,D24-1)))) | G24: =IF(D24="","",$G$2) | H24: =$B$7 -> 0.475 | I24: 112.21 | J24: 8.31 | K24: =IF(D24="","",IF(MONTH(F23)=MONTH(F24),(F24-F23)/DAY(EOMONTH(F24,0)),DAY(EOMONTH(F23,0)-F23)/DAY(EOMONTH(F23,0))+DAY(F24-EOMONTH(F23,0))/DAY(EOMONTH(F24,0)))) | L24: =IF(D24="","",G24-M24) | M24: =IF(D24="","",O23*((1+$B$7/12)^(K24)-1)) | O24: =IF(D24="","",O23+M24-G24+N24) | P24: 348.91 | R24: 0 | S24: 0 | T24: =T23+M24 -> 554.71386 | U24: 2500
D25: =IF(D24="", "",IF(D24+1>$B$8,"",D24+1)) | E25: =IF(D25="","","Due Pmt") | F25: =IF(D25="", "", IF($B$5="Byweekly", F24+14,IF($B$5="End of month",EOMONTH(F24, 1),EDATE($F$2,D25-1)))) | G25: =IF(D25="","",$G$2) | H25: =$B$7 -> 0.475 | I25: 114.23 | J25: 6.29 | K25: =IF(D25="","",IF(MONTH(F24)=MONTH(F25),(F25-F24)/DAY(EOMONTH(F25,0)),DAY(EOMONTH(F24,0)-F24)/DAY(EOMONTH(F24,0))+DAY(F25-EOMONTH(F24,0))/DAY(EOMONTH(F25,0)))) | L25: =IF(D25="","",G25-M25) | M25: =IF(D25="","",O24*((1+$B$7/12)^(K25)-1)) | O25: =IF(D25="","",O24+M25-G25+N25) | P25: 234.68 | R25: 0 | S25: 0 | T25: =T24+M25 -> 554.71386 | U25: 2500
A26: Balance date | B26: =F13 -> 45190 | D26: =IF(D25="", "",IF(D25+1>$B$8,"",D25+1)) | E26: =IF(D26="","","Due Pmt") | F26: =IF(D26="", "", IF($B$5="Byweekly", F25+14,IF($B$5="End of month",EOMONTH(F25, 1),EDATE($F$2,D26-1)))) | G26: =IF(D26="","",$G$2) | H26: =$B$7 -> 0.475 | I26: 116.29 | J26: 4.23 | K26: =IF(D26="","",IF(MONTH(F25)=MONTH(F26),(F26-F25)/DAY(EOMONTH(F26,0)),DAY(EOMONTH(F25,0)-F25)/DAY(EOMONTH(F25,0))+DAY(F26-EOMONTH(F25,0))/DAY(EOMONTH(F26,0)))) | L26: =IF(D26="","",G26-M26) | M26: =IF(D26="","",O25*((1+$B$7/12)^(K26)-1)) | O26: =IF(D26="","",O25+M26-G26+N26) | P26: 118.39 | R26: 0 | S26: 0 | T26: =T25+M26 -> 554.71386 | U26: 2500
D27: =IF(D26="", "",IF(D26+1>$B$8,"",D26+1)) | E27: =IF(D27="","","Due Pmt") | F27: =IF(D27="", "", IF($B$5="Byweekly", F26+14,IF($B$5="End of month",EOMONTH(F26, 1),EDATE($F$2,D27-1)))) | G27: =IF(D27="","",$G$2) | H27: =$B$7 -> 0.475 | I27: 118.39 | J27: 2.13 | K27: =IF(D27="","",IF(MONTH(F26)=MONTH(F27),(F27-F26)/DAY(EOMONTH(F27,0)),DAY(EOMONTH(F26,0)-F26)/DAY(EOMONTH(F26,0))+DAY(F27-EOMONTH(F26,0))/DAY(EOMONTH(F27,0)))) | L27: =IF(D27="","",G27-M27) | M27: =IF(D27="","",O26*((1+$B$7/12)^(K27)-1)) | O27: =IF(D27="","",O26+M27-G27+N27) | P27: 0 | R27: 0 | S27: 0 | T27: =T26+M27 -> 554.71386 | U27: 2500
A28: Peter | B28: abc
D30: Totals | G30: =SUM(G2:G29) -> 3103.827 | I30: =SUM(I2:I27) -> 2500 | J30: =SUM(J2:J27) -> 633.52 | L30: =SUM(L2:L29) -> 2549.1131 | M30: =ROUND(SUM(M2:M29),2) -> 554.71 | N30: =SUM(N2:N27) -> 0 | R30: =SUM(R2:R27) -> 0 | S30: =SUM(S2:S27) -> 0

Sheet word Merge field
A1: Loan number | B1: current date | C1: Origination Date | D1: Last payment date | E1: First Payment date | F1: Payment frequency | G1: principal | H1: Total Interest | I1: total obligation | J1: annual nominal rate | K1: number of payments | L1: payment amount | M1: Norminal | N1: Effective | O1: APR Norminal | P1: APR Effective | Q1: Compounding period | R1: Borrower Name | S1: Borrower Address | T1: Borrower Phone | U1: Borrower Email | V1: Borrower Bank Transit | W1: Borrower Bank Institution | X1: Borrower Bank Account | Y1: Name2 | Z1: Address2 | AA1: Phone 2 | AB1: Email2 | AC1: Bank Transit2 | AD1: Bank Institution2 | AE1: Bank Account2 | AF1: Name3 | AG1: Address3 | AH1: Phone 3 | AI1: Email3 | AJ1: Bank Transit3 | AK1: Bank Institution3 | AL1: Bank Account3 | AM1: Name4 | AN1: Address4 | AO1: Phone 4 | AP1: Email4 | AQ1: Bank Transit4 | AR1: Bank Institution4 | AS1: Bank Account4
A2: ='Details and table'!B1 -> 110022 | B2: ='Details and table'!B2 -> 44845 | C2: ='Details and table'!B3 -> 44846 | D2: ='Details and table'!B20 -> 45190 | E2: ='Details and table'!B4 -> 44855 | F2: ='Details and table'!B5 -> Monthly | G2: ='Details and table'!B6 -> 2500 | H2: ='Details and table'!B21 -> 554.71 | I2: =G2+H2 -> 3054.71 | J2: ='Details and table'!B7*100 -> 47.5 | K2: ='Details and table'!B8 -> 12 | L2: =ROUND('Details and table'!B10,2) -> 258.65 | M2: ='Details and table'!B13*100 -> 47.5 | N2: ='Details and table'!B14*100 -> 59.34 | O2: ='Details and table'!B16*100 -> 47.5 | P2: ='Details and table'!B17*100 -> 59.335189 | Q2: ='Details and table'!B19 -> Monthly | R2: ='Loan info'!B12 -> John Doe | S2: ='Loan info'!C12 -> 123 AAA St | T2: ='Loan info'!D12 -> 111-222-2222 | U2: ='Loan info'!E12 -> john.doe@gmail.com | V2: ='Loan info'!F12 -> 98988 | W2: ='Loan info'!G12 -> 004 | X2: ='Loan info'!H12 -> 1212345 | Y2: ='Loan info'!B13 -> Bo Be | Z2: ='Loan info'!C13 -> 234 BBB St | AA2: ='Loan info'!D13 -> 111-222-3333 | AB2: ='Loan info'!E13 -> bo.be@gmail.com | AC2: ='Loan info'!F13 | AD2: ='Loan info'!G13 | AE2: ='Loan info'!H13 | AF2: ='Loan info'!B14 -> Sam Yan | AG2: ='Loan info'!C14 -> 888 CCC St | AH2: ='Loan info'!D14 -> 999-000-9999 | AI2: ='Loan info'!E14 -> sam.yan@gmail.com | AJ2: ='Loan info'!F14 | AK2: ='Loan info'!G14 | AL2: ='Loan info'!H14 | AM2: ='Loan info'!B15 -> Mike Dow | AN2: ='Loan info'!C15 -> 999 DDD St | AO2: ='Loan info'!D15 -> 939-020-3933 | AP2: ='Loan info'!E15 -> mike.dow@gmail.com | AQ2: ='Loan info'!F15 | AR2: ='Loan info'!G15 | AS2: ='Loan info'!H15
F19: ='Details and table'!D20
F20: ='Details and table'!D21
F21: ='Details and table'!D22
F22: ='Details and table'!D23
F23: ='Details and table'!D24
F24: ='Details and table'!D25
F25: ='Details and table'!D26
F26: ='Details and table'!D27

Sheet Source
A1: Byweekly
A2: Monthly
A3: End of Month
A5: Min loan term | B5: 1
A6: MAX loan term | B6: 26
A8: Due Pmt
A9: Paid Pmt
A10: E-transferred
